dioc.py
setup.py
dioc.egg-info/PKG-INFO
dioc.egg-info/SOURCES.txt
dioc.egg-info/dependency_links.txt
dioc.egg-info/entry_points.txt
dioc.egg-info/requires.txt
dioc.egg-info/top_level.txt