Metadata-Version: 1.1
Name: dioc
Version: 0.0.9
Summary: `dioc` is a package for DigitalOcean.
Home-page: https://pypi.python.org/pypi/dioc
Author: Saito Tsutomu
Author-email: tsutomu@kke.co.jp
License: PSFL
Keywords: dioc
Platform: UNKNOWN
Classifier: Development Status :: 1 - Planning
Classifier: License :: OSI Approved :: Python Software Foundation License
Classifier: Programming Language :: Python
Classifier: Topic :: Software Development
